vcc/__init__.py
vcc/rpc.py
vcc/service.py
vcc/test.py
vcc/tools.py
vcc/vcc.py
vcc_lib-0.3.11.dist-info/METADATA
vcc_lib-0.3.11.dist-info/WHEEL
vcc_lib-0.3.11.dist-info/RECORD
