Metadata-Version: 2.1
Name: vcc_lib
Version: 0.3.11
Summary: vcc base library
License: MIT
Author: Calvinlin
Requires-Python: >=3.10,<4.0
Classifier: License :: OSI Approved :: MIT License
Classifier: Programming Language :: Python :: 3
Classifier: Programming Language :: Python :: 3.10
Classifier: Programming Language :: Python :: 3.11
Requires-Dist: redis (>=5.0.1,<6.0.0)
